{"timestamp": "2025-06-04T20:53:21.063275", "data": [{"title": "Government Scholarships in India 2025: Category, Steps to Apply ...", "description": "", "link": "https://www.collegedekho.com/government-scholarships-csp-1", "source": "", "deadline": "Not specified", "type": "Scholarship", "relevance_score": 0}, {"title": "Scholarship for College Students in 2025: A Complete Guide - Chegg India", "description": "", "link": "https://www.cheggindia.com/career-guidance/scholarship-for-college-students/", "source": "", "deadline": "Not specified", "type": "Scholarship", "relevance_score": 0}, {"title": "75 Government of India scholarships 2025-26 [Updated]", "description": "", "link": "https://www.wemakescholars.com/other/government-of-india/scholarships", "source": "", "deadline": "Not specified", "type": "Scholarship", "relevance_score": 0}, {"title": "ICCR Scholarships 2025-26", "description": "", "link": "https://www.indiaingreece.gov.in/page/iccr-scholarships-2025-26/", "source": "", "deadline": "Not specified", "type": "Scholarship", "relevance_score": 0}, {"title": "Global Scholarships 2025 | Study With Us - Newcastle University", "description": "", "link": "https://www.ncl.ac.uk/study/global-scholarships-2025/", "source": "", "deadline": "Not specified", "type": "Scholarship", "relevance_score": 0}, {"title": "Top Scholarships For Undergraduate Students In 2025", "description": "", "link": "https://edufundglobal.com/2025/01/07/top-scholarships-for-undergraduate-students-in-2025/", "source": "", "deadline": "Not specified", "type": "Scholarship", "relevance_score": 0}, {"title": "List of Available Scholarships in 2025 (Fully Funded, High Funded)", "description": "", "link": "https://www.scholarshipdiary.com/list-of-available-scholarships-in-2025/", "source": "", "deadline": "Not specified", "type": "Scholarship", "relevance_score": 0}, {"title": "Undergraduate Scholarships For International Students 2025-2026", "description": "", "link": "https://www.scholarshiptab.com/undergraduate", "source": "", "deadline": "Not specified", "type": "Scholarship", "relevance_score": 0}, {"title": "International Students Scholarships in the U.S and Canada", "description": "", "link": "https://www.mpowerfinancing.com/scholarships", "source": "", "deadline": "Not specified", "type": "Scholarship", "relevance_score": 0}, {"title": "Merit Based Scholarships for College Students in 2025 - UNIGO", "description": "", "link": "https://www.unigo.com/scholarships/merit-based", "source": "", "deadline": "Not specified", "type": "Scholarship", "relevance_score": 0}, {"title": "Top merit-based scholarships for you - Sallie", "description": "", "link": "https://www.sallie.com/scholarships/types/merit-based", "source": "", "deadline": "Not specified", "type": "Scholarship", "relevance_score": 0}, {"title": "Scholarships Archive - CollegeAdvisor", "description": "", "link": "https://www.collegeadvisor.com/merit-based-scholarships/", "source": "", "deadline": "Not specified", "type": "Scholarship", "relevance_score": 0}, {"title": "Guide To Merit Scholarships And Financial Aid - Affordable Colleges Online", "description": "", "link": "https://www.affordablecollegesonline.org/financial-aid/scholarships/merit-based-scholarships/", "source": "", "deadline": "Not specified", "type": "Scholarship", "relevance_score": 0}, {"title": "Top Merit-Based Scholarships for Master's Students", "description": "", "link": "https://mastergradschools.com/financing-your-master/top-merit-based-scholarships-for-masters-students", "source": "", "deadline": "Not specified", "type": "Scholarship", "relevance_score": 0}, {"title": "Need-Based Financial Aid: How it Works and How to Qualify - Debt.com", "description": "", "link": "https://www.debt.com/student-loan/financial-aid/need-based/", "source": "", "deadline": "Not specified", "type": "Scholarship", "relevance_score": 0}, {"title": "What Is Need-Based Financial Aid? - Business Insider", "description": "", "link": "https://www.businessinsider.com/personal-finance/student-loans/need-based-financial-aid?op=1", "source": "", "deadline": "Not specified", "type": "Scholarship", "relevance_score": 0}, {"title": "What is Need-Based Financial Aid? - College Money Tips", "description": "", "link": "https://collegemoneytips.com/what-is-need-based-financial-aid/", "source": "", "deadline": "Not specified", "type": "Scholarship", "relevance_score": 0}, {"title": "Need-based Financial Aid: What It Is & How To Qualify - Bankrate", "description": "", "link": "https://www.bankrate.com/loans/student-loans/need-based-financial-aid/", "source": "", "deadline": "Not specified", "type": "Scholarship", "relevance_score": 0}, {"title": "25 Scholarships to Apply for in 2025 - Fastweb", "description": "", "link": "https://www.fastweb.com/college-scholarships/articles/scholarships-to-apply-for-in-2025", "source": "", "deadline": "Not specified", "type": "Scholarship", "relevance_score": 0}, {"title": "Undergraduate Scholarships", "description": "", "link": "https://www.scholarships.com/financial-aid/college-scholarships/scholarships-by-grade-level/undergraduate-scholarships", "source": "", "deadline": "Not specified", "type": "Scholarship", "relevance_score": 0}, {"title": "Top 100+ Undergraduate Scholarships in May 2025", "description": "", "link": "https://scholarships360.org/scholarships/undergraduate-scholarships/", "source": "", "deadline": "Not specified", "type": "Scholarship", "relevance_score": 0}, {"title": "50+ Scholarships for College Students to Apply for in 2025", "description": "", "link": "https://accessscholarships.com/blog/50-scholarships-for-college-students/", "source": "", "deadline": "Not specified", "type": "Scholarship", "relevance_score": 0}, {"title": "New Scholarships for Undergraduates in 2025 - UNIGO", "description": "", "link": "https://www.unigo.com/scholarships/undergraduate-students", "source": "", "deadline": "Not specified", "type": "Scholarship", "relevance_score": 0}, {"title": "Scholarships for Graduate Students in 2025 - Unigo.com", "description": "", "link": "https://www.unigo.com/scholarships/graduate-students", "source": "", "deadline": "Not specified", "type": "Scholarship", "relevance_score": 0}, {"title": "Graduate School 1st Year Scholarships", "description": "", "link": "https://www.scholarships.com/financial-aid/college-scholarships/scholarship-directory/school-year/graduate-school-1st-year", "source": "", "deadline": "Not specified", "type": "Scholarship", "relevance_score": 0}, {"title": "120 Scholarships for Graduate Students with June 2025 Deadlines", "description": "", "link": "https://bold.org/scholarships/by-year/graduate-students-scholarships/", "source": "", "deadline": "Not specified", "type": "Scholarship", "relevance_score": 0}, {"title": "11 Best Scholarships For Graduate Students In 2025 - Prosperity For All", "description": "", "link": "https://www.prosperityforamerica.org/scholarships-for-graduate-students/", "source": "", "deadline": "Not specified", "type": "Scholarship", "relevance_score": 0}, {"title": "Top STEM Scholarships To Apply For In 2025 - CGH", "description": "", "link": "https://collegegranthub.com/blog/stem-scholarships/", "source": "", "deadline": "Not specified", "type": "Scholarship", "relevance_score": 0}, {"title": "Scholarships for STEM Programs (2025) - Latest Update", "description": "", "link": "https://teacheducator.com/scholarships-for-stem-programs/", "source": "", "deadline": "Not specified", "type": "Scholarship", "relevance_score": 0}, {"title": "Top 10 Scholarships for STEM Students - editionnews.com", "description": "", "link": "https://www.editionnews.com/post/top-10-scholarships-for-stem-students", "source": "", "deadline": "Not specified", "type": "Scholarship", "relevance_score": 0}, {"title": "STEM Scholarships", "description": "", "link": "https://www.scholarships.com/financial-aid/college-scholarships/scholarships-by-type/stem-scholarships", "source": "", "deadline": "Not specified", "type": "Scholarship", "relevance_score": 0}, {"title": "Top 404 STEM Scholarships\u269b\ufe0f in May 2025", "description": "", "link": "https://scholarships360.org/scholarships/stem-scholarships/", "source": "", "deadline": "Not specified", "type": "Scholarship", "relevance_score": 0}, {"title": "Scholarships for International Students in USA for 2025", "description": "", "link": "https://www.edvisehub.com/scholarships-for-international-students-in-usa-for-2025/", "source": "", "deadline": "Not specified", "type": "Scholarship", "relevance_score": 0}, {"title": "Scholarships in USA for International Students 2025", "description": "", "link": "https://nspscholarships.com/scholarships-in-usa-for-international-students/", "source": "", "deadline": "Not specified", "type": "Scholarship", "relevance_score": 0}, {"title": "Scholarships in USA for international students 2025", "description": "", "link": "https://www.scholarshipsads.com/category/country/usa-scholarships/", "source": "", "deadline": "Not specified", "type": "Scholarship", "relevance_score": 0}, {"title": "List of Fully Funded Masters Scholarships in USA 2025", "description": "", "link": "https://scholarshiproar.com/fully-funded-masters-scholarships-in-usa/", "source": "", "deadline": "Not specified", "type": "Scholarship", "relevance_score": 0}, {"title": "Fully Funded Scholarships in USA 2025 for International Students", "description": "", "link": "https://www.universityliving.com/blog/student-finances/fully-funded-scholarships-in-usa/", "source": "", "deadline": "Not specified", "type": "Scholarship", "relevance_score": 0}, {"title": "Female Scholarships - Scholarships.com", "description": "", "link": "https://www.scholarships.com/financial-aid/college-scholarships/scholarship-directory/gender/female/", "source": "", "deadline": "Not specified", "type": "Scholarship", "relevance_score": 0}, {"title": "Women In Technology Scholarship 2025", "description": "", "link": "https://theglobalscholarship.org/scholarships/women-in-technology-scholarship-2025?source=main", "source": "", "deadline": "Not specified", "type": "Scholarship", "relevance_score": 0}, {"title": "Tech scholarships for Women in the U.S and Canada (2025)", "description": "", "link": "https://www.techloy.com/tech-scholarships-for-women-in-the-u-s-and-canada-2025/", "source": "", "deadline": "Not specified", "type": "Scholarship", "relevance_score": 0}, {"title": "Women STEM Scholarships: A 2025 List That Does Not Miss", "description": "", "link": "https://collegelifemadeeasy.com/women-in-stem-scholarships/", "source": "", "deadline": "Not specified", "type": "Scholarship", "relevance_score": 0}, {"title": "Top Women in STEM Scholarships to Apply for in 2025: Funding ...", "description": "", "link": "https://dawnheimer.com/women-in-stem-scholarships-2025-opportunities/", "source": "", "deadline": "Not specified", "type": "Scholarship", "relevance_score": 0}, {"title": "African American Scholarships - JLV College Counseling", "description": "", "link": "https://jlvcollegecounseling.com/scholarships/minority/african-american/", "source": "", "deadline": "Not specified", "type": "Scholarship", "relevance_score": 0}, {"title": "Top 166 Scholarships for Minority Students in May 2025", "description": "", "link": "https://scholarships360.org/scholarships/minority-scholarships/", "source": "", "deadline": "Not specified", "type": "Scholarship", "relevance_score": 0}, {"title": "African American Scholarships", "description": "", "link": "https://www.scholarships.com/financial-aid/college-scholarships/scholarship-directory/race/african-american", "source": "", "deadline": "Not specified", "type": "Scholarship", "relevance_score": 0}, {"title": "Best 2025 Minority Scholarships You Should Apply For - UNIGO", "description": "", "link": "https://www.unigo.com/scholarships/minority", "source": "", "deadline": "Not specified", "type": "Scholarship", "relevance_score": 0}, {"title": "Minority Scholarships", "description": "", "link": "https://www.scholarships.com/financial-aid/college-scholarships/scholarships-by-type/minority-scholarships", "source": "", "deadline": "Not specified", "type": "Scholarship", "relevance_score": 0}]}